reversible_anonymizer/__init__.py
reversible_anonymizer/anonymizer.py
reversible_anonymizer/cli.py
reversible_anonymizer/common.py
reversible_anonymizer/config.py
reversible_anonymizer/exceptions.py
reversible_anonymizer/models.py
reversible_anonymizer/utils.py
reversible_anonymizer/cache/__init__.py
reversible_anonymizer/cache/base.py
reversible_anonymizer/cache/memcache_adapter.py
reversible_anonymizer/cache/memory_cache.py
reversible_anonymizer/infotypes/__init__.py
reversible_anonymizer/infotypes/catalog.py
reversible_anonymizer/storage/__init__.py
reversible_anonymizer/storage/base.py
reversible_anonymizer/storage/firestore_adapter.py
reversible_anonymizer/storage/secure_firestore_adapter.py
reversible_anonymizer-1.0.12.dist-info/METADATA
reversible_anonymizer-1.0.12.dist-info/WHEEL
reversible_anonymizer-1.0.12.dist-info/entry_points.txt
reversible_anonymizer-1.0.12.dist-info/top_level.txt
reversible_anonymizer-1.0.12.dist-info/RECORD
