Metadata-Version: 2.2
Name: reversible-anonymizer
Version: 1.0.12
Summary: Enterprise-grade reversible anonymization using Google Cloud DLP
Home-page: https://github.com/ainaomotayo/reversible-anonymizer
Author: Omotayo Aina
Author-email: Omotayo Aina <ainaomotayo@secureaiguard.com>
Project-URL: Homepage, https://github.com/ainaomotayo/reversible-anonymizer
Project-URL: Bug Tracker, https://github.com/ainaomotayo/reversible-anonymizer/issues
Project-URL: Documentation, https://reversible-anonymizer.readthedocs.io/
Classifier: Development Status :: 5 - Production/Stable
Classifier: Intended Audience :: Developers
Classifier: Intended Audience :: Information Technology
Classifier: Intended Audience :: Healthcare Industry
Classifier: Intended Audience :: Financial and Insurance Industry
Classifier: License :: OSI Approved :: MIT License
Classifier: Programming Language :: Python :: 3
Classifier: Programming Language :: Python :: 3.8
Classifier: Programming Language :: Python :: 3.9
Classifier: Programming Language :: Python :: 3.10
Classifier: Programming Language :: Python :: 3.11
Classifier: Operating System :: OS Independent
Classifier: Topic :: Security
Classifier: Topic :: Security :: Cryptography
Classifier: Topic :: Software Development :: Libraries :: Python Modules
Requires-Python: >=3.8
Requires-Dist: faker>=8.0.0
Requires-Dist: google-cloud-dlp>=3.0.0
Requires-Dist: google-cloud-firestore>=2.0.0
Requires-Dist: google-cloud-service-usage>=1.0.0
Requires-Dist: cryptography>=38.0.0
Requires-Dist: python-memcached>=1.59
Requires-Dist: google-cloud-memcache>=1.4.1
Provides-Extra: dev
Requires-Dist: pytest>=7.0.0; extra == "dev"
Requires-Dist: pytest-cov>=3.0.0; extra == "dev"
Requires-Dist: black>=22.0.0; extra == "dev"
Requires-Dist: isort>=5.10.0; extra == "dev"
Requires-Dist: mypy>=0.950; extra == "dev"
Requires-Dist: flake8>=4.0.0; extra == "dev"
Provides-Extra: docs
Requires-Dist: sphinx>=4.0.0; extra == "docs"
Requires-Dist: sphinx-rtd-theme>=1.0.0; extra == "docs"
Requires-Dist: myst-parser>=0.18.0; extra == "docs"
Provides-Extra: memcache
Requires-Dist: python-memcached>=1.59; extra == "memcache"
Requires-Dist: google-cloud-memcache>=1.4.1; extra == "memcache"
